{
  "ComponentIndexes": {},
  "ControlUniqueGuids": {},
  "ControlUniqueIds": {
    "App": 1,
    "Circle1": 14,
    "Circle1_1": 27,
    "Group1": 16,
    "Group1_1": 31,
    "Home Page": 5,
    "Home Page_1": 21,
    "Icon1": 15,
    "Icon1_1": 28,
    "Icon2_23": 39,
    "Icon2_45": 40,
    "Icon2_46": 41,
    "Icon2_47": 42,
    "Icon2_48": 43,
    "Icon2_49": 44,
    "Icon3_36": 47,
    "Icon3_37": 48,
    "Icon3_38": 49,
    "Icon3_39": 50,
    "Icon3_40": 51,
    "Image1": 4,
    "Image2": 8,
    "Image2_1": 23,
    "Image3": 9,
    "Image3_1": 24,
    "Image4": 10,
    "Image5": 17,
    "Image5_1": 26,
    "Image7": 32,
    "Label2_30": 33,
    "Label2_31": 34,
    "Label2_32": 35,
    "Label2_33": 36,
    "Label2_34": 37,
    "Label2_35": 38,
    "Landing Page": 3,
    "Rectangle1": 7,
    "Rectangle1_1": 13,
    "Rectangle1_2": 12,
    "Rectangle1_3": 22,
    "Rectangle1_4": 30,
    "Rectangle1_5": 29,
    "Timer1": 20
  },
  "FunctionParamsInvariantScripts": {},
  "FunctionParamsInvariantScriptsOnInstances": {},
  "HeaderLastSavedDateTimeUTC": "12/12/2022 13:18:22",
  "IsLegacyComponentAllowGlobalScopeCase": false,
  "LocalConnectionIDReferences": {},
  "LocalDatabaseReferencesAsEmpty": false,
  "LocalResourceFileNames": {
    "Background": "cd282525-7fa3-4011-878b-3c2ff770a728.png",
    "download (2)": "930fa758-2f70-4490-b613-c3ffadbd616e.png",
    "download (3)": "0947bae7-a1b8-46c1-8f4b-40f448c179d1.png",
    "download screen": "1b22d55b-8b68-401d-8862-081655326e0d.png",
    "Panda Logo": "9f6a8b41-8b52-4383-809b-3dbb3a773dbc.svg",
    "Picture1": "c16690a5-4f51-4a9e-83e7-bd7f0408c62e.png"
  },
  "LocalResourceRootPaths": {
    "Background": "https://docserverpwaprodweu.blob.core.windows.net/b2d12089-cb9d-452b-b2df-b92913443752-1/resource/eddd3d58-b44b-4593-8860-5501ae55f8a7.png?sv=2017-04-17&sr=b&sig=7ugvAeetvvSdSVXePqTVyZTUtKk0VpPeZQPXpwY3NaQ%3D&spr=https&se=2022-12-13T12%3A05%3A26Z&sp=r",
    "download (2)": "https://docserverpwaprodweu.blob.core.windows.net/b2d12089-cb9d-452b-b2df-b92913443752-1/resource/c5822ad9-e0fa-4d20-9940-9c66267ecda2.png?sv=2017-04-17&sr=b&sig=Klq1HQDsdqI5amhpbCTl9RHFOhwoFynm%2BjHXuRbSdxA%3D&spr=https&se=2022-12-13T11%3A49%3A47Z&sp=r",
    "download (3)": "https://docserverpwaprodweu.blob.core.windows.net/b2d12089-cb9d-452b-b2df-b92913443752-1/resource/27dac569-f419-4347-abe8-153d1b3e85f5.png?sv=2017-04-17&sr=b&sig=AqEFnrxwYNgvYva0GKEXOOetwJjZf8CdkXNa5BnEhQU%3D&spr=https&se=2022-12-13T12%3A01%3A53Z&sp=r",
    "download screen": "https://docserverpwaprodweu.blob.core.windows.net/b2d12089-cb9d-452b-b2df-b92913443752-1/resource/4fbb0656-bb73-4273-a491-e885e07464ce.png?sv=2017-04-17&sr=b&sig=WGmvhRW9yzk3TTfc6WLoHLfj8yw1Uv5MvCUjVFfCWoA%3D&spr=https&se=2022-12-13T12%3A13%3A09Z&sp=r",
    "Panda Logo": "https://docserverpwaprodweu.blob.core.windows.net/b2d12089-cb9d-452b-b2df-b92913443752-1/resource/676c3271-8190-4d96-9c79-0c6d89d1bf30.svg?sv=2017-04-17&sr=b&sig=u3%2B%2FF2MZ0sVzbVIcORhHpB3ZXrJ1mYy4492yBMJ0rJU%3D&spr=https&se=2022-12-13T12%3A01%3A39Z&sp=r",
    "Picture1": "https://docserverpwaprodweu.blob.core.windows.net/b2d12089-cb9d-452b-b2df-b92913443752-1/resource/ad4683ab-c48a-4fcb-b479-26c222e6aeb4.png?sv=2017-04-17&sr=b&sig=9Zc8uQVCR0eSEKi%2BhWgP46%2Bl2p3A0qLmvd1%2FXZXOgEA%3D&spr=https&se=2022-12-13T13%3A20%3A01Z&sp=r"
  },
  "OrderComponentMetadata": {},
  "OrderComponentTemplate": {},
  "OrderDataSource": {},
  "OrderGroupControls": {
    "Group1": {
      "Circle1": 1,
      "Icon1": 0
    },
    "Group1_1": {
      "Circle1_1": 1,
      "Icon1_1": 0
    }
  },
  "OrderPcfTemplate": {},
  "OrderTemplate": {},
  "OrderXMLTemplate": {
    "circle": 3,
    "icon": 4,
    "image": 0,
    "label": 5,
    "rectangle": 2,
    "timer": 1
  },
  "PublishOrderIndices": {
    "App": 0,
    "Circle1": 7,
    "Circle1_1": 32,
    "Group1": 8,
    "Group1_1": 33,
    "Home Page": 0,
    "Home Page_1": 0,
    "Icon1": 9,
    "Icon1_1": 34,
    "Icon2_23": 23,
    "Icon2_45": 17,
    "Icon2_46": 20,
    "Icon2_47": 26,
    "Icon2_48": 28,
    "Icon2_49": 30,
    "Icon3_36": 19,
    "Icon3_37": 22,
    "Icon3_38": 25,
    "Icon3_39": 25,
    "Icon3_40": 25,
    "Image1": 0,
    "Image2": 3,
    "Image2_1": 13,
    "Image3": 4,
    "Image3_1": 14,
    "Image4": 5,
    "Image5": 6,
    "Image5_1": 15,
    "Image7": 16,
    "Label2_30": 18,
    "Label2_31": 21,
    "Label2_32": 24,
    "Label2_33": 27,
    "Label2_34": 29,
    "Label2_35": 31,
    "Landing Page": 0,
    "Rectangle1": 2,
    "Rectangle1_1": 11,
    "Rectangle1_2": 10,
    "Rectangle1_3": 12,
    "Rectangle1_4": 36,
    "Rectangle1_5": 35,
    "Timer1": 1
  },
  "ResourcesJsonIndices": {
    "Image-Background": 4,
    "Image-download (2)": 0,
    "Image-download (3)": 3,
    "Image-download screen": 5,
    "Image-Panda Logo": 2,
    "Image-Picture1": 6,
    "Image-SampleImage": 1
  },
  "RuleScreenIdWithoutScreen": {},
  "TemplateVersions": {},
  "VolatileProperties": {
    "AnalysisLoadTime": 0.0254798,
    "ControlCount": {
      "circle": 2,
      "group": 1,
      "icon": 13,
      "image": 6,
      "label": 6,
      "rectangle": 6,
      "screen": 1
    },
    "ErrorCount": 0
  },
  "WasLocalDatabaseReferencesEmpty": true
}